comparerdspg/__init__.py
comparerdspg-1.0.0.dist-info/METADATA
comparerdspg-1.0.0.dist-info/WHEEL
comparerdspg-1.0.0.dist-info/top_level.txt
comparerdspg-1.0.0.dist-info/RECORD
