Metadata-Version: 2.1
Name: comparerdspg
Version: 1.0.0
Summary: Comparing RDS parameter group in AWS account
Home-page: https://github.com/tanmay6414/comparerdspg
Author: Tanmay Varade
Author-email: <tanmayvarade235@gmail.com>
License: UNKNOWN
Keywords: python,compare,RDS,parameter,group,AWS,devops
Platform: UNKNOWN
Classifier: Programming Language :: Python :: 3
Classifier: License :: OSI Approved :: MIT License
Classifier: Operating System :: Unix
Classifier: Operating System :: MacOS :: MacOS X
Classifier: Operating System :: Microsoft :: Windows
Requires-Dist: pandas
